MSEplots/__init__.py
MSEplots/plots.py
MSEplots_pkg-2.5.3.dist-info/METADATA
MSEplots_pkg-2.5.3.dist-info/RECORD
MSEplots_pkg-2.5.3.dist-info/WHEEL
MSEplots_pkg-2.5.3.dist-info/top_level.txt
