Metadata-Version: 2.1
Name: MSEplots-pkg
Version: 2.5.3
Summary: A package for static energy plots based on MetPy
Home-page: https://github.com/weiming9115/MSEplots
Author: Wei-Ming Tsai
Author-email: wxt108@rsmas.miami.edu
License: UNKNOWN
Platform: UNKNOWN
Classifier: Programming Language :: Python :: 3
Classifier: License :: OSI Approved :: MIT License
Classifier: Operating System :: OS Independent
Requires-Dist: metpy
